{"id":"6f1ba42c-f92e-492e-81ef-895411fa4882","serviceId":"brewers-service","requestId":"dd45cc73-ccce-4cb5-8d19-a9aa04b55cb1","requestType":"EGRUL","xsltId":8,"clientInternalNumber":"3565361655","responseId":"2a0ffc5b-8296-11ee-bb54-005056ad53ff","messageId":"1f6ee333-8296-11ee-a84c-a20e283aea67","requestContent":{"requestId":"dd45cc73-ccce-4cb5-8d19-a9aa04b55cb1","innUl":"5446021423"},"requestTimestamp":"2023-11-14T05:32:57.896+0300","updateTimestamp":"2023-11-14T05:34:03.566+0300","responseContent":{"svUL":{"dateVyp":"2023-10-19","ogrn":"1215400022661","dateOgrn":"2021-05-26","inn":"5446021423","kpp":"540301001","sprOPF":"ОКОПФ","codeOPF":"12300","fullNameOPF":"Общества с ограниченной ответственностью","svNameUL":{"nameULFull":"ОБЩЕСТВО С ОГРАНИЧЕННОЙ ОТВЕТСТВЕННОСТЬЮ ПРОИЗВОДСТВЕННАЯ КОМПАНИЯ \"ВЫЛКОВО\"","nameULShort":"","grnDate":{"grn":"2235400387055","dateNote":"2023-05-04"},"svNameULShort":{"nameShort":"ООО ПК \"ВЫЛКОВО\"","grnDate":{"grn":"2235400387055","dateNote":"2023-05-04"}}},"svAddressUL":{"svMNUL":{"idNum":"8dea00e3-9aab-4d8e-887c-ef2aaa546456","region":"54","nameRegion":"Новосибирская область","municipRayon":{"vidCode":"2","name":"ГОРОД НОВОСИБИРСК"},"gorodSelPoselen":{"vidCode":"","name":""},"naselenPunkt":{"vid":"Г","name":"НОВОСИБИРСК"},"grnDate":{"grn":"2235400991373","dateNote":"2023-10-16"}},"svAdrULFIAS":{"idNum":"ffa08ecc-61da-467f-aebc-20a1eb8e1d9b","index":"630024","region":"54","nameRegion":"Новосибирская область","municipRayon":{"vidCode":"2","name":"ГОРОД НОВОСИБИРСК"},"naselenPunkt":{"vid":"Г","name":"НОВОСИБИРСК"},"elUlDorSety":{"type":"УЛ","name":"СИБИРЯКОВ-ГВАРДЕЙЦЕВ"},"zdanie":{"type":"Д.","number":"50"},"grnDate":{"grn":"2235400991373","dateNote":"2023-10-16"}}},"svStatus":{"codeStatusUl":"","nameStatusUl":""},"svUstCap":{"nameVidCap":"УСТАВНЫЙ КАПИТАЛ","sumCap":"20000000","grnDate":{"grn":"2225400308813","dateNote":"2022-04-01"}},"svDolzhnFL":{"grnDatePerv":{"grn":"2235400710785","dateNote":"2023-08-03"},"svFL":{"lastName":"МУРАВЬЕВ","firstName":"КОНСТАНТИН","patronymic":"СЕРГЕЕВИЧ","innFL":"541002801670","grnDate":{"grn":"2235400710785","dateNote":"2023-08-03"}},"svDolzhn":{"vidDolzhn":"02","nameVidDolzhn":"Руководитель юридического лица","nameDolzhn":"ДИРЕКТОР","grnDate":{"grn":"2235400710785","dateNote":"2023-08-03"}}},"svUcheredit":{"uchrFL":[{"grnDatePerv":{"grn":"1215400022661","dateNote":"2021-05-26"},"svFL":{"lastName":"КОСУЛИНА","firstName":"ИРИНА","patronymic":"ВЛАДИМИРОВНА","innFL":"541002356797","grnDate":{"grn":"2225400308813","dateNote":"2022-04-01"}}}]}}},"kafkaPartition":4,"kafkaOffset":71704,"route":"OUT","attachmentPath":null,"state":"OUTGOING","archivedStatus":true,"queuedStatus":true}